{
   "CodeGenerationMode": 2,
   "ContextClassName": "VETLYContext",
   "ContextNamespace": "Data",
   "DefaultDacpacSchema": null,
   "FilterSchemas": false,
   "IncludeConnectionString": false,
   "ModelNamespace": "Models",
   "OutputContextPath": "Data",
   "OutputPath": "Models",
   "PreserveCasingWithRegex": true,
   "ProjectRootNamespace": "VETLY_API",
   "Schemas": null,
   "SelectedHandlebarsLanguage": 0,
   "SelectedToBeGenerated": 0,
   "Tables": [
      {
         "Name": "[dbo].[Veterinaria]",
         "ObjectType": 0
      }
   ],
   "UiHint": "desktop-iai1knv.VETLY.dbo",
   "UncountableWords": null,
   "UseBoolPropertiesWithoutDefaultSql": false,
   "UseDatabaseNames": false,
   "UseDateOnlyTimeOnly": false,
   "UseDbContextSplitting": false,
   "UseFluentApiOnly": true,
   "UseHandleBars": false,
   "UseHierarchyId": false,
   "UseInflector": false,
   "UseLegacyPluralizer": false,
   "UseManyToManyEntity": false,
   "UseNoDefaultConstructor": false,
   "UseNoObjectFilter": false,
   "UseNodaTime": false,
   "UseNullableReferences": false,
   "UseSchemaFolders": false,
   "UseSpatial": false,
   "UseT4": false
}